setup.py
dsp_probability/Binomialdistribution.py
dsp_probability/Gaussiandistribution.py
dsp_probability/Generaldistribution.py
dsp_probability/__init__.py
dsp_probability.egg-info/PKG-INFO
dsp_probability.egg-info/SOURCES.txt
dsp_probability.egg-info/dependency_links.txt
dsp_probability.egg-info/not-zip-safe
dsp_probability.egg-info/top_level.txt