Metadata-Version: 1.0
Name: dsp-probability
Version: 0.1
Summary: Gaussian, Binomial distributions
Home-page: UNKNOWN
Author: Jose A Mancilla
Author-email: jt.mancilla@gmail.com
License: UNKNOWN
Platform: UNKNOWN
